{"DescricaoEstacao":"","ServicosEquipamentos":{"PassagemDesnivelada":"não","QuantidadeTapetesRolantes":"0","QuantidadeEscadasRolantes":"0","QuantidadeElevadores":"0","TelefonesInfoPublico":"Não","Atm":"Não","Bilheteira":"Não","BilheteiraTelefone":"808 208 208","HorarioFuncionamento":"","DepositoAutobagagem":"Não","Metro":"Não","ParqueEstacionamento":"Não","PostoInformacoes":"Não","PostoPerdidosAchados":"Não","SalaEspera":"Não","SistemaEncPessoasDefVisual":"Não","Autocarros":"Não","Barcos":"Não","CabinesTelefonicas":"Não","CaixasCorreioCTT":"Não","InstalacoesSanitarias":"Não","MaquinasVendaBilhetes":"Não","InformacaoSonora":"Sim","MonitoresPartidasChegadas":"Não","AcessoInternet":"Não","RentCar":"Não","RentCarTelefone":"","Taxis":"Não","TelefoneTaxis":"","ZonaEstacionamento":"Não","QuiosqueMultimediaREFER":"Não","QuiosqueMultimedia":null,"VideoVigilancia":"Não"},"FotografiasEstacao":[],"tiposDeComboiosServemEstacao":[{"Nome":"SUBURBANOS"}],"OperadoresServemEstacao":[{"Nome":"CP Porto"}],"HorarioEstacao":"24/24","Morada":"Rua Doutor Mario Rosas da Silva, 4425 Ermesinde","AcessoMobilidadeReduzida":"Sim","AeroportoNome":"Sá Carneiro","AeroportoDistancia":"Entre 10 e 20 Km","FarmaciaNome":"","FarmaciaDistancia":"","BombeirosNome":"Bombeiros Voluntários de Moreira da Maia\n                   ","BombeirosTelefone":"229 481 018","PoliciaNome":"PSP - Esquadra de Águas Santas\n                                                    ","PoliciaTelefone":"229 713 537","HospitalNome":"Hospital Pedro Hispano\n                                                                                                                  ","HospitalTelefone":"Tel. 229 391 000","Coordenadas":"lat=41.199436710000001 ; long=-8.5562049800000004","NodeID":"9403046","Nome":"Águas Santas","Linha":"Linha do Minho","AnoContrucao":"2004","EPClassificadoInteresse":"","Telefone":"","Bilheteira":null,"HorarioBilheteira":null,"EquipamentomobilidadeReduzidaPlataformas":"","TarifaEstacionamento":null,"EstacionamentoBicicletas":"Não","CidadeProxima":"Rio Tinto","CidadeProximaDistancia":"Entre 1 e 5 Km","CentroCidadeProximaDistancia":"< 1 Km","PK":"6,418"}