{"DescricaoEstacao":"","ServicosEquipamentos":{"PassagemDesnivelada":"superior","QuantidadeTapetesRolantes":"0","QuantidadeEscadasRolantes":"0","QuantidadeElevadores":"3","TelefonesInfoPublico":"","Atm":"Não","Bilheteira":"Não","BilheteiraTelefone":"808 208 208","HorarioFuncionamento":"","DepositoAutobagagem":"Não","Metro":"Não","ParqueEstacionamento":"Sim","PostoInformacoes":"Não","PostoPerdidosAchados":"Não","SalaEspera":"Não","SistemaEncPessoasDefVisual":"Não","Autocarros":"Não","Barcos":"Não","CabinesTelefonicas":"Não","CaixasCorreioCTT":"Não","InstalacoesSanitarias":"Não","MaquinasVendaBilhetes":"Sim","InformacaoSonora":"Sim","MonitoresPartidasChegadas":"Sim","AcessoInternet":"Não","RentCar":"Não","RentCarTelefone":"","Taxis":"Sim","TelefoneTaxis":"","ZonaEstacionamento":"Não","QuiosqueMultimediaREFER":"Não","QuiosqueMultimedia":null,"VideoVigilancia":"Não"},"FotografiasEstacao":[],"tiposDeComboiosServemEstacao":[{"Nome":"SUBURBANOS"}],"OperadoresServemEstacao":[{"Nome":"CP Lisboa"}],"HorarioEstacao":"","Morada":"","AcessoMobilidadeReduzida":"Sim","AeroportoNome":"Aeroporto da Portela em Lisboa","AeroportoDistancia":"Entre 5 e 10 Km","FarmaciaNome":"Farmácia Santa Bárbara","FarmaciaDistancia":"< 1 Km","BombeirosNome":"Bombeiros Voluntários de Moscavide","BombeirosTelefone":"219 458 640","PoliciaNome":"PSP Divisão de Loures\nCentral de ocorrências","PoliciaTelefone":"219 946 760","HospitalNome":"Hospital Curry Cabral","HospitalTelefone":"217 924 200","Coordenadas":"lat=38.779802570000001 ; long=-9.0997777089999996","NodeID":"9431047","Nome":"Moscavide","Linha":"Linha do Norte","AnoContrucao":"","EPClassificadoInteresse":"","Telefone":"","Bilheteira":null,"HorarioBilheteira":null,"EquipamentomobilidadeReduzidaPlataformas":"","TarifaEstacionamento":null,"EstacionamentoBicicletas":"Não","CidadeProxima":"Sacavém","CidadeProximaDistancia":"Entre 1 e 5 Km","CentroCidadeProximaDistancia":"< 1 Km","PK":"7,644"}