{"DescricaoEstacao":"","ServicosEquipamentos":{"PassagemDesnivelada":"não","QuantidadeTapetesRolantes":"0","QuantidadeEscadasRolantes":"0","QuantidadeElevadores":"0","TelefonesInfoPublico":"Não","Atm":"Não","Bilheteira":"Não","BilheteiraTelefone":"808 208 208","HorarioFuncionamento":"","DepositoAutobagagem":"Não","Metro":"Não","ParqueEstacionamento":"Não","PostoInformacoes":"Não","PostoPerdidosAchados":"Não","SalaEspera":"Sim","SistemaEncPessoasDefVisual":"Não","Autocarros":"Não","Barcos":"Não","CabinesTelefonicas":"Sim","CaixasCorreioCTT":"Não","InstalacoesSanitarias":"Sim","MaquinasVendaBilhetes":"Sim","InformacaoSonora":"Sim","MonitoresPartidasChegadas":"Não","AcessoInternet":"Não","RentCar":"Não","RentCarTelefone":"","Taxis":"Sim","TelefoneTaxis":"","ZonaEstacionamento":"Não","QuiosqueMultimediaREFER":"Não","QuiosqueMultimedia":null,"VideoVigilancia":"Sim"},"FotografiasEstacao":[],"tiposDeComboiosServemEstacao":[{"Nome":"SUBURBANOS"},{"Nome":"REGIONAIS"}],"OperadoresServemEstacao":[{"Nome":"CP Porto"}],"HorarioEstacao":"24/24","Morada":"Largo da Estação,345  3885-528 Esmoriz","AcessoMobilidadeReduzida":"Sim","AeroportoNome":"Francisco Sá Caneiro (Porto) - Pedras Rubras 4470-558 Maia - 229 432 400 - 41 14' 08\" N 008 40' 41\" W","AeroportoDistancia":"> 20 Km","FarmaciaNome":"FARMÁCIA MODERNA","FarmaciaDistancia":"Entre 1 e 5 Km","BombeirosNome":"B.V. de Esmoriz\n","BombeirosTelefone":"256 752 122 / 256 755 450","PoliciaNome":"GNR - Posto Territorial de Esmoriz\n\n","PoliciaTelefone":"256 750 240 / 256 753 800","HospitalNome":"Hospital de São Sebastião\n\n","HospitalTelefone":"256 379 700","Coordenadas":"lat=40.962727778 ; long=-8.635519444","NodeID":"9438406","Nome":"Esmoriz","Linha":"Linha do Norte","AnoContrucao":"1997","EPClassificadoInteresse":"","Telefone":"","Bilheteira":null,"HorarioBilheteira":null,"EquipamentomobilidadeReduzidaPlataformas":"","TarifaEstacionamento":null,"EstacionamentoBicicletas":"Não","CidadeProxima":"Esmoriz","CidadeProximaDistancia":"< 1 Km","CentroCidadeProximaDistancia":"< 1 Km","PK":"311,900"}