{"DescricaoEstacao":"","ServicosEquipamentos":{"PassagemDesnivelada":"não","QuantidadeTapetesRolantes":"0","QuantidadeEscadasRolantes":"0","QuantidadeElevadores":"0","TelefonesInfoPublico":"Sim","Atm":"Não","Bilheteira":"Não","BilheteiraTelefone":"808 208 208","HorarioFuncionamento":"","DepositoAutobagagem":"Não","Metro":"Não","ParqueEstacionamento":"Não","PostoInformacoes":"Não","PostoPerdidosAchados":"Não","SalaEspera":"Sim","SistemaEncPessoasDefVisual":"Não","Autocarros":"Não","Barcos":"Não","CabinesTelefonicas":"Não","CaixasCorreioCTT":"Não","InstalacoesSanitarias":"Não","MaquinasVendaBilhetes":"Não","InformacaoSonora":"","MonitoresPartidasChegadas":"","AcessoInternet":"Não","RentCar":"Não","RentCarTelefone":"","Taxis":"Sim","TelefoneTaxis":"271709114 Fornos","ZonaEstacionamento":"Não","QuiosqueMultimediaREFER":"Não","QuiosqueMultimedia":null,"VideoVigilancia":"Não"},"FotografiasEstacao":[],"tiposDeComboiosServemEstacao":[{"Nome":"REGIONAIS"}],"OperadoresServemEstacao":[{"Nome":"CP Regional"}],"HorarioEstacao":"Não aplicavel","Morada":"Rua da Estação - Gouveia Gare - 3530-011 MMangualde","AcessoMobilidadeReduzida":"Não","AeroportoNome":"Porto","AeroportoDistancia":"> 20 Km","FarmaciaNome":"Farmacia da Abrunhosa","FarmaciaDistancia":"Entre 5 e 10 Km","BombeirosNome":"Bomb. Vol. Mangualde \nSecção Abrunhosa-a-Velha\t\t\t","BombeirosTelefone":"232 651 951","PoliciaNome":"GNR Mangualde\t\t\t\t\t","PoliciaTelefone":"232 622 258","HospitalNome":"Hospital S. Teotónio","HospitalTelefone":"232 420 500","Coordenadas":"lat=40.573344800000001 ; long=-7.6021392069999996","NodeID":"9448165","Nome":"Gouveia","Linha":"Linha da Beira Alta","AnoContrucao":"","EPClassificadoInteresse":"","Telefone":"","Bilheteira":null,"HorarioBilheteira":null,"EquipamentomobilidadeReduzidaPlataformas":"","TarifaEstacionamento":null,"EstacionamentoBicicletas":"Não","CidadeProxima":"","CidadeProximaDistancia":"","CentroCidadeProximaDistancia":"Entre 1 e 5 Km","PK":"144,208"}