{"DescricaoEstacao":"","ServicosEquipamentos":{"PassagemDesnivelada":"inferior","QuantidadeTapetesRolantes":"0","QuantidadeEscadasRolantes":"0","QuantidadeElevadores":"2","TelefonesInfoPublico":"Não","Atm":"Sim","Bilheteira":"Sim","BilheteiraTelefone":"808 208 208","HorarioFuncionamento":"6.00 / 23.00","DepositoAutobagagem":"Não","Metro":"Não","ParqueEstacionamento":"Não","PostoInformacoes":"Não","PostoPerdidosAchados":"Não","SalaEspera":"Sim","SistemaEncPessoasDefVisual":"Não","Autocarros":"Não","Barcos":"Não","CabinesTelefonicas":"Sim","CaixasCorreioCTT":"Não","InstalacoesSanitarias":"Sim","MaquinasVendaBilhetes":"Não","InformacaoSonora":"Sim","MonitoresPartidasChegadas":"Não","AcessoInternet":"Não","RentCar":"Não","RentCarTelefone":"","Taxis":"Sim","TelefoneTaxis":"271239163/966797467","ZonaEstacionamento":"Não","QuiosqueMultimediaREFER":"Não","QuiosqueMultimedia":null,"VideoVigilancia":"Sim"},"FotografiasEstacao":[],"tiposDeComboiosServemEstacao":[{"Nome":"INTERCIDADES"},{"Nome":"REGIONAIS"}],"OperadoresServemEstacao":[{"Nome":"CP Longo Curso"},{"Nome":"CP Regional"}],"HorarioEstacao":"00:00-24:00","Morada":"Largo 1º. de Dezembro - 6300-851 Guarda ","AcessoMobilidadeReduzida":"Sim","AeroportoNome":"Porto","AeroportoDistancia":"> 20 Km","FarmaciaNome":"Moderna","FarmaciaDistancia":"< 1 Km","BombeirosNome":"Bombeiros Voluntários Egitanienses","BombeirosTelefone":"271 222 115","PoliciaNome":"PSP da Guarda","PoliciaTelefone":"271 222 022","HospitalNome":"Unidade de Saúde Local da Guarda","HospitalTelefone":"271 200 200","Coordenadas":"lat=40.551803489999998 ; long=-7.2395225989999998","NodeID":"9449007","Nome":"Guarda","Linha":"Linha da Beira Alta","AnoContrucao":"","EPClassificadoInteresse":"","Telefone":"","Bilheteira":null,"HorarioBilheteira":null,"EquipamentomobilidadeReduzidaPlataformas":"","TarifaEstacionamento":"","EstacionamentoBicicletas":"Não","CidadeProxima":"Guarda","CidadeProximaDistancia":"no local","CentroCidadeProximaDistancia":"Entre 1 e 5 Km","PK":"206,337"}