{"DescricaoEstacao":"","ServicosEquipamentos":{"PassagemDesnivelada":"","QuantidadeTapetesRolantes":"0","QuantidadeEscadasRolantes":"0","QuantidadeElevadores":"0","TelefonesInfoPublico":"","Atm":"","Bilheteira":"","BilheteiraTelefone":"808 208 208","HorarioFuncionamento":"","DepositoAutobagagem":"","Metro":"","ParqueEstacionamento":"","PostoInformacoes":"","PostoPerdidosAchados":"","SalaEspera":"","SistemaEncPessoasDefVisual":"","Autocarros":"Não","Barcos":"","CabinesTelefonicas":"","CaixasCorreioCTT":"","InstalacoesSanitarias":"","MaquinasVendaBilhetes":"","InformacaoSonora":"","MonitoresPartidasChegadas":"","AcessoInternet":"","RentCar":"","RentCarTelefone":"","Taxis":"","TelefoneTaxis":"","ZonaEstacionamento":"Não","QuiosqueMultimediaREFER":"","QuiosqueMultimedia":null,"VideoVigilancia":""},"FotografiasEstacao":[],"tiposDeComboiosServemEstacao":[],"OperadoresServemEstacao":[],"HorarioEstacao":"","Morada":"","AcessoMobilidadeReduzida":"","AeroportoNome":"","AeroportoDistancia":"","FarmaciaNome":"","FarmaciaDistancia":"","BombeirosNome":"","BombeirosTelefone":"","PoliciaNome":"","PoliciaTelefone":"","HospitalNome":"","HospitalTelefone":"","Coordenadas":"lat=38.606314699999999 ; long=-7.8774104779999998","NodeID":"9483063","Nome":"Garraia (A)","Linha":"Linha de Évora","AnoContrucao":"","EPClassificadoInteresse":"","Telefone":"","Bilheteira":null,"HorarioBilheteira":null,"EquipamentomobilidadeReduzidaPlataformas":"","TarifaEstacionamento":null,"EstacionamentoBicicletas":"Não","CidadeProxima":"","CidadeProximaDistancia":"","CentroCidadeProximaDistancia":"","PK":"122,900"}